taskrepo/__init__.py
taskrepo/__version__.py
taskrepo/cli/__init__.py
taskrepo/cli/main.py
taskrepo/cli/commands/__init__.py
taskrepo/cli/commands/add.py
taskrepo/cli/commands/add_link.py
taskrepo/cli/commands/append.py
taskrepo/cli/commands/archive.py
taskrepo/cli/commands/cancelled.py
taskrepo/cli/commands/changelog.py
taskrepo/cli/commands/config.py
taskrepo/cli/commands/delete.py
taskrepo/cli/commands/done.py
taskrepo/cli/commands/edit.py
taskrepo/cli/commands/extend.py
taskrepo/cli/commands/history.py
taskrepo/cli/commands/in_progress.py
taskrepo/cli/commands/info.py
taskrepo/cli/commands/list.py
taskrepo/cli/commands/move.py
taskrepo/cli/commands/repos_search.py
taskrepo/cli/commands/search.py
taskrepo/cli/commands/sync.py
taskrepo/cli/commands/tui.py
taskrepo/cli/commands/unarchive.py
taskrepo/cli/commands/update.py
taskrepo/cli/commands/upgrade.py
taskrepo/cli/notifiers/__init__.py
taskrepo/cli/notifiers/upgrade_notifier.py
taskrepo/core/__init__.py
taskrepo/core/config.py
taskrepo/core/repository.py
taskrepo/core/task.py
taskrepo/logo/logo-taskrepo.png
taskrepo/tui/__init__.py
taskrepo/tui/conflict_resolver.py
taskrepo/tui/display.py
taskrepo/tui/prompts.py
taskrepo/tui/task_tui.py
taskrepo/utils/__init__.py
taskrepo/utils/async_sync.py
taskrepo/utils/banner.py
taskrepo/utils/changelog_parser.py
taskrepo/utils/conflict_detection.py
taskrepo/utils/countdown.py
taskrepo/utils/date_parser.py
taskrepo/utils/display_constants.py
taskrepo/utils/duration.py
taskrepo/utils/file_validation.py
taskrepo/utils/github.py
taskrepo/utils/helpers.py
taskrepo/utils/history.py
taskrepo/utils/history_cache.py
taskrepo/utils/homebrew_checker.py
taskrepo/utils/id_mapping.py
taskrepo/utils/merge.py
taskrepo/utils/paths.py
taskrepo/utils/sorting.py
taskrepo/utils/sync_history.py
taskrepo/utils/time_format.py
taskrepo-0.10.17.dist-info/METADATA
taskrepo-0.10.17.dist-info/WHEEL
taskrepo-0.10.17.dist-info/entry_points.txt
taskrepo-0.10.17.dist-info/licenses/LICENSE
taskrepo-0.10.17.dist-info/RECORD
