Metadata-Version: 2.4
Name: taskrepo
Version: 0.10.17
Summary: TaskWarrior-inspired CLI for managing tasks as markdown files in git repositories
Project-URL: Homepage, https://github.com/henriqueslab/TaskRepo
Project-URL: Repository, https://github.com/henriqueslab/TaskRepo
Project-URL: Issues, https://github.com/henriqueslab/TaskRepo/issues
Author-email: Ricardo Henriques <paxcalpt@gmail.com>
License-File: LICENSE
Keywords: cli,git,markdown,productivity,task-management,taskwarrior
Classifier: Development Status :: 3 - Alpha
Classifier: Intended Audience :: Developers
Classifier: License :: OSI Approved :: MIT License
Classifier: Operating System :: OS Independent
Classifier: Programming Language :: Python :: 3
Classifier: Programming Language :: Python :: 3.10
Classifier: Programming Language :: Python :: 3.11
Classifier: Programming Language :: Python :: 3.12
Classifier: Topic :: Office/Business :: Scheduling
Classifier: Topic :: Software Development
Requires-Python: >=3.10
Requires-Dist: click>=8.0.0
Requires-Dist: dateparser>=1.0.0
Requires-Dist: gitpython>=3.1.0
Requires-Dist: henriqueslab-updater>=1.2.0
Requires-Dist: packaging>=20.0
Requires-Dist: prompt-toolkit>=3.0.0
Requires-Dist: python-dateutil>=2.8.0
Requires-Dist: pyyaml>=6.0.0
Requires-Dist: rich>=13.0.0
Provides-Extra: dev
Requires-Dist: mypy>=1.0; extra == 'dev'
Requires-Dist: pre-commit>=4.2.0; extra == 'dev'
Requires-Dist: pytest-cov>=4.0; extra == 'dev'
Requires-Dist: pytest<10.0,>=7.4; extra == 'dev'
Requires-Dist: ruff>=0.12.2; extra == 'dev'
Requires-Dist: types-dateparser>=1.0.0; extra == 'dev'
Requires-Dist: types-python-dateutil>=2.8.0; extra == 'dev'
Requires-Dist: types-pyyaml>=6.0.0; extra == 'dev'
